shifaa/__init__.py
shifaa/datasets/README.md
shifaa/datasets/__init__.py
shifaa/datasets/loader.py
shifaa/rag/README.md
shifaa/rag/__init__.py
shifaa/rag/document_processor.py
shifaa/rag/medical_categories.json
shifaa/rag/medical_rag.py
shifaa/rag/utils.py
shifaa/rag/vector_db.py
shifaa/vision/README.md
shifaa/vision/__init__.py
shifaa/vision/model_manager.py
shifaa/vision/vision_factory.py
shifaa/vision/classification/BrainTumor/BrainTumorClassifier.py
shifaa/vision/classification/DR/DiabeticRetinopathyClassifier.py
shifaa/vision/classification/Eye_Disease/EyeDiseaseClassifier.py
shifaa/vision/classification/covid/COVIDClassifier.py
shifaa/vision/segmentation/Breast_Cancer/breast_cancer.py
shifaa/vision/segmentation/CT_Heart/CT_Heart.py
shifaa/vision/segmentation/Skin_Cancer/skin_cancer.py
shifaa-0.1.0.dist-info/licenses/LICENSE
shifaa-0.1.0.dist-info/METADATA
shifaa-0.1.0.dist-info/WHEEL
shifaa-0.1.0.dist-info/entry_points.txt
shifaa-0.1.0.dist-info/top_level.txt
shifaa-0.1.0.dist-info/RECORD
