Metadata-Version: 2.4
Name: shifaa
Version: 0.1.0
Summary: Arabic Medical AI Platform - Datasets, RAG, and Vision Models
Author-email: Ahmed Selim <ahmedselimmahmoud1@gmail.com>
Maintainer-email: Ahmed Selim <ahmedselimmahmoud1@gmail.com>
License: MIT
Project-URL: Homepage, https://github.com/AhmedSeelim/shifaa
Project-URL: Repository, https://github.com/AhmedSeelim/shifaa
Project-URL: Bug Tracker, https://github.com/AhmedSeelim/shifaa/issues
Project-URL: Source Code, https://github.com/AhmedSeelim/shifaa
Project-URL: HuggingFace, https://huggingface.co/Ahmed-Selem
Project-URL: Colab Notebook, https://colab.research.google.com/github/AhmedSeelim/shifaa/blob/main/Shifaa_Examples.ipynb
Keywords: medical,healthcare,arabic,ai,machine-learning,deep-learning,medical-imaging,computer-vision,nlp,rag,retrieval-augmented-generation,medical-diagnosis,mena,middle-east,dataset,consultation,classification,segmentation
Classifier: Development Status :: 4 - Beta
Classifier: Intended Audience :: Healthcare Industry
Classifier: Intended Audience :: Science/Research
Classifier: Intended Audience :: Developers
Classifier: Intended Audience :: Education
Classifier: Topic :: Scientific/Engineering :: Artificial Intelligence
Classifier: Topic :: Scientific/Engineering :: Medical Science Apps.
Classifier: Topic :: Software Development :: Libraries :: Python Modules
Classifier: License :: OSI Approved :: MIT License
Classifier: Programming Language :: Python :: 3
Classifier: Programming Language :: Python :: 3.8
Classifier: Programming Language :: Python :: 3.9
Classifier: Programming Language :: Python :: 3.10
Classifier: Programming Language :: Python :: 3.11
Classifier: Programming Language :: Python :: 3.12
Classifier: Natural Language :: Arabic
Classifier: Natural Language :: English
Classifier: Operating System :: OS Independent
Classifier: Framework :: Jupyter
Requires-Python: >=3.8
License-File: LICENSE
Requires-Dist: datasets==4.4.1
Requires-Dist: pydantic==2.12.5
Requires-Dist: langchain==1.1.0
Requires-Dist: langchain-core==1.1.0
Requires-Dist: langchain_google_genai==3.2.0
Requires-Dist: torch
Requires-Dist: sentence-transformers==3.4.1
Requires-Dist: chromadb==0.6.3
Requires-Dist: tokenizers==0.22.0
Requires-Dist: matplotlib>=3.5.0
Requires-Dist: torchvision
Provides-Extra: dev
Requires-Dist: pydicom>=2.4.0; extra == "dev"
Requires-Dist: pytest>=7.0.0; extra == "dev"
Requires-Dist: pytest-cov>=4.0.0; extra == "dev"
Requires-Dist: black>=22.0.0; extra == "dev"
Requires-Dist: flake8>=5.0.0; extra == "dev"
Requires-Dist: mypy>=0.990; extra == "dev"
Requires-Dist: sphinx>=5.0.0; extra == "dev"
Requires-Dist: sphinx-rtd-theme>=1.0.0; extra == "dev"
Requires-Dist: jupyter>=1.0.0; extra == "dev"
Requires-Dist: ipython>=8.0.0; extra == "dev"
Requires-Dist: pre-commit>=3.0.0; extra == "dev"
Provides-Extra: docs
Requires-Dist: sphinx>=5.0.0; extra == "docs"
Requires-Dist: sphinx-rtd-theme>=1.0.0; extra == "docs"
Requires-Dist: myst-parser>=0.18.0; extra == "docs"
Requires-Dist: sphinx-autodoc-typehints>=1.19.0; extra == "docs"
Provides-Extra: all
Requires-Dist: pytest>=7.0.0; extra == "all"
Requires-Dist: pytest-cov>=4.0.0; extra == "all"
Requires-Dist: black>=22.0.0; extra == "all"
Requires-Dist: flake8>=5.0.0; extra == "all"
Requires-Dist: mypy>=0.990; extra == "all"
Requires-Dist: sphinx>=5.0.0; extra == "all"
Requires-Dist: sphinx-rtd-theme>=1.0.0; extra == "all"
Requires-Dist: jupyter>=1.0.0; extra == "all"
Requires-Dist: ipython>=8.0.0; extra == "all"
Requires-Dist: pre-commit>=3.0.0; extra == "all"
Requires-Dist: myst-parser>=0.18.0; extra == "all"
Requires-Dist: sphinx-autodoc-typehints>=1.19.0; extra == "all"
Dynamic: license-file
